flow_models/__init__.py
flow_models/anonymize.py
flow_models/convert.py
flow_models/cut.py
flow_models/fit.py
flow_models/generate.py
flow_models/hist.py
flow_models/hist_np.py
flow_models/merge.py
flow_models/plot.py
flow_models/series.py
flow_models/series_plot.py
flow_models/sort.py
flow_models/summary.py
flow_models/elephants/__init__.py
flow_models/elephants/plot_entropy.py
flow_models/elephants/simulate_data.py
flow_models/first_mirror/__init__.py
flow_models/first_mirror/simulate.py
flow_models/lib/__init__.py
flow_models/lib/cryptopan.py
flow_models/lib/data.py
flow_models/lib/io.py
flow_models/lib/kde.py
flow_models/lib/mix.py
flow_models/lib/ml.py
flow_models/lib/plot.py
flow_models/lib/util.py
flow_models-2.2.dist-info/LICENSE
flow_models-2.2.dist-info/METADATA
flow_models-2.2.dist-info/WHEEL
flow_models-2.2.dist-info/top_level.txt
flow_models-2.2.dist-info/RECORD
