Metadata-Version: 2.1
Name: flow_models
Version: 2.2
Summary: A framework for analysis and modeling of IP network flows
Home-page: https://github.com/piotrjurkiewicz/flow-models
Author: Piotr Jurkiewicz
Author-email: piotr.jerzy.jurkiewicz@gmail.com
License: MIT
Classifier: Programming Language :: Python :: 3
Classifier: License :: OSI Approved :: MIT License
Classifier: Operating System :: POSIX
Classifier: Development Status :: 5 - Production/Stable
Classifier: Environment :: Console
Classifier: Topic :: Internet
Classifier: Topic :: Scientific/Engineering :: Information Analysis
Classifier: Topic :: Scientific/Engineering :: Visualization
Classifier: Topic :: System :: Networking
Classifier: Intended Audience :: Science/Research
Classifier: Intended Audience :: System Administrators
Classifier: Intended Audience :: Telecommunications Industry
License-File: LICENSE
